julynter/__init__.py
julynter/__main__.py
julynter/_version.py
julynter/config.py
julynter/handlers.py
julynter/oldcmd.py
julynter/util.py
julynter/cmd/__init__.py
julynter/cmd/env.py
julynter/cmd/experiment.py
julynter/cmd/extractpipenv.py
julynter/cmd/julynterlab.py
julynter/cmd/run.py
julynter/cmd/validate.py
julynter/environments/__init__.py
julynter/environments/base.py
julynter/environments/conda.py
julynter/environments/docker.py
julynter/environments/imports.py
julynter/environments/orchestrator.py
julynter/environments/process.py
julynter/environments/venv.py
julynter/kernel/__init__.py
julynter/kernel/ast_visitors.py
julynter/kernel/jcomm.py
julynter/kernel/linter.py
julynter/labextension/build_log.json
julynter/labextension/package.json
julynter/labextension/static/lib_index_js.477fc1f8a8e005d3f2cf.js
julynter/labextension/static/lib_index_js.477fc1f8a8e005d3f2cf.js.map
julynter/labextension/static/node_modules_sha1_sha1_js.2ad062fe3f3c159ec1f6.js
julynter/labextension/static/node_modules_sha1_sha1_js.2ad062fe3f3c159ec1f6.js.map
julynter/labextension/static/remoteEntry.97e8704e71f01e3ea5e3.js
julynter/labextension/static/remoteEntry.97e8704e71f01e3ea5e3.js.map
julynter/labextension/static/style.js
julynter/labextension/static/style_index_js.f8b76192cc094e5c85a4.js
julynter/labextension/static/style_index_js.f8b76192cc094e5c85a4.js.map
julynter/labextension/static/vendors-node_modules_css-loader_dist_runtime_api_js-node_modules_css-loader_dist_runtime_cssW-72eba1.3e180da3445b4a300f3f.js
julynter/labextension/static/vendors-node_modules_css-loader_dist_runtime_api_js-node_modules_css-loader_dist_runtime_cssW-72eba1.3e180da3445b4a300f3f.js.map
julynter/runner/__init__.py
julynter/runner/compare.py
julynter/runner/preprocessors.py
julynter/runner/runner.py
julynter-0.4.2.data/data/etc/jupyter/jupyter_notebook_config.d/julynter.json
julynter-0.4.2.data/data/etc/jupyter/jupyter_server_config.d/julynter.json
julynter-0.4.2.dist-info/LICENSE
julynter-0.4.2.dist-info/METADATA
julynter-0.4.2.dist-info/WHEEL
julynter-0.4.2.dist-info/entry_points.txt
julynter-0.4.2.dist-info/top_level.txt
julynter-0.4.2.dist-info/RECORD
