Metadata-Version: 2.1
Name: julynter
Version: 0.4.2
Summary: A quality checker for Jupyter
Home-page: https://github.com/dew-uff/julynter
Author: Joao Felipe Pimentel
Author-email: joaofelipenp@gmail.com
License: BSD-3-Clause
Keywords: Jupyter,JupyterLab,JupyterLab3
Platform: Linux
Platform: Mac OS X
Platform: Windows
Classifier: License :: OSI Approved :: BSD License
Classifier: Programming Language :: Python
Classifier: Programming Language :: Python :: 3
Classifier: Programming Language :: Python :: 3.5
Classifier: Programming Language :: Python :: 3.6
Classifier: Programming Language :: Python :: 3.7
Classifier: Programming Language :: Python :: 3.8
Classifier: Programming Language :: Python :: 3.9
Classifier: Framework :: Jupyter
Classifier: Framework :: Jupyter :: JupyterLab
Classifier: Framework :: Jupyter :: JupyterLab :: 3
Classifier: Framework :: Jupyter :: JupyterLab :: Extensions
Classifier: Framework :: Jupyter :: JupyterLab :: Extensions :: Prebuilt
Requires-Python: >=3.6
License-File: LICENSE
Requires-Dist: jupyter-server (<2requests,>=1.6)
Requires-Dist: requests-futures
Requires-Dist: timeout-decorator
Requires-Dist: jupyter
Requires-Dist: nbformat
Requires-Dist: pathlib2 ; python_version <= "3.4"
Requires-Dist: pathlib2 ; python_version == "2.7"
